hulearn/__init__.py
hulearn/common.py
hulearn/datasets.py
hulearn/this.py
hulearn/classification/__init__.py
hulearn/classification/functionclassifier.py
hulearn/classification/interactiveclassifier.py
hulearn/data/fish.zip
hulearn/data/titanic.zip
hulearn/experimental/__init__.py
hulearn/experimental/interactive.py
hulearn/experimental/ruler.py
hulearn/images/blue.png
hulearn/images/cyan.png
hulearn/images/green.png
hulearn/images/purple.png
hulearn/images/red.png
hulearn/outlier/__init__.py
hulearn/outlier/functionoutlier.py
hulearn/outlier/interactiveoutlier.py
hulearn/preprocessing/__init__.py
hulearn/preprocessing/interactivepreprocessor.py
hulearn/preprocessing/pipetransformer.py
hulearn/regression/__init__.py
hulearn/regression/functionregressor.py
hulearn/static/parcoords/d3.min.js
hulearn/static/parcoords/d3.parcoords.css
hulearn/static/parcoords/d3.parcoords.js
hulearn/static/parcoords/template.html
tests/__init__.py
tests/conftest.py
tests/test_docstrings.py
human_learn-0.3.5.dist-info/LICENSE
human_learn-0.3.5.dist-info/METADATA
human_learn-0.3.5.dist-info/WHEEL
human_learn-0.3.5.dist-info/top_level.txt
human_learn-0.3.5.dist-info/RECORD
